[
  {
    "id": "notif-1",
    "title": "New Document Uploaded",
    "message": "Electrical Layout Drawing v1.5 has been uploaded and requires review",
    "type": "Info",
    "timestamp": "2024-12-12T16:45:00Z",
    "read": false,
    "userId": "user-2",
    "link": "/edms"
  },
  {
    "id": "notif-2",
    "title": "Risk Alert",
    "message": "High priority risk identified: Budget Overrun in Water Supply Network project",
    "type": "Warning",
    "timestamp": "2024-12-10T14:20:00Z",
    "read": false,
    "userId": "user-1",
    "link": "/risk"
  },
  {
    "id": "notif-3",
    "title": "Task Completed",
    "message": "Site Survey and Soil Testing has been completed",
    "type": "Success",
    "timestamp": "2024-12-08T09:30:00Z",
    "read": true,
    "userId": "user-2",
    "link": "/scheduling"
  },
  {
    "id": "notif-4",
    "title": "Budget Approval Required",
    "message": "Budget approval pending for Power Distribution System project",
    "type": "Warning",
    "timestamp": "2024-12-05T11:15:00Z",
    "read": false,
    "userId": "user-1",
    "link": "/cost"
  },
  {
    "id": "notif-5",
    "title": "Schedule Variance Alert",
    "message": "Road Base Layer Construction is showing a delay of 5 days",
    "type": "Warning",
    "timestamp": "2024-12-03T10:00:00Z",
    "read": true,
    "userId": "user-2",
    "link": "/scheduling"
  },
  {
    "id": "notif-6",
    "title": "Document Approved",
    "message": "Road Design Drawing - Section A v2.1 has been approved",
    "type": "Success",
    "timestamp": "2024-12-01T15:20:00Z",
    "read": true,
    "userId": "user-4",
    "link": "/edms"
  }
]


